safepy/__init__.py
safepy/_async_batch.py
safepy/batching_mechanism.py
safepy/combination.py
safepy/copy_exception.py
safepy/handle_bounded_methods.py
safepy/retry_mechanism.py
safepy/throttling.py
safepy/timeout.py
safepy-0.1.0a0.dist-info/DESCRIPTION.rst
safepy-0.1.0a0.dist-info/METADATA
safepy-0.1.0a0.dist-info/RECORD
safepy-0.1.0a0.dist-info/WHEEL
safepy-0.1.0a0.dist-info/metadata.json
safepy-0.1.0a0.dist-info/top_level.txt
