Metadata-Version: 2.0
Name: safepy
Version: 0.1.0a0
Summary: Safety belt for your Python distributed services.
Home-page: https://github.com/prokopst/safepy
Author: Stanislav Prokop
Author-email: UNKNOWN
License: Apache 2 License
Keywords: safety microservice microservices
Platform: UNKNOWN
Classifier: Development Status :: 3 - Alpha
Classifier: Intended Audience :: Developers
Classifier: Topic :: Software Development :: Libraries
Classifier: License :: OSI Approved :: Apache Software License
Classifier: Programming Language :: Python :: 3.5
Classifier: Programming Language :: Python :: 3.6
